dict_from_dict/__init__.py
dict_from_dict/argparse_helper.py
dict_from_dict/cli.py
dict_from_dict/core.py
dict_from_dict/main.py
dict_from_dict_tests/__init__.py
dict_from_dict-0.0.4.dist-info/LICENSE
dict_from_dict-0.0.4.dist-info/METADATA
dict_from_dict-0.0.4.dist-info/WHEEL
dict_from_dict-0.0.4.dist-info/entry_points.txt
dict_from_dict-0.0.4.dist-info/top_level.txt
dict_from_dict-0.0.4.dist-info/RECORD
